ezpose/__init__.py
ezpose/ezpose.py
ezpose-0.1.11.dist-info/METADATA
ezpose-0.1.11.dist-info/WHEEL
ezpose-0.1.11.dist-info/top_level.txt
ezpose-0.1.11.dist-info/RECORD
