Metadata-Version: 2.4
Name: ezpose
Version: 0.1.11
Summary: Add your description here
Requires-Python: >=3.9
Requires-Dist: numpy<2
Requires-Dist: scipy>=1.13.1
